README.rst
setup.cfg
setup.py
src/Baluster.egg-info/PKG-INFO
src/Baluster.egg-info/SOURCES.txt
src/Baluster.egg-info/dependency_links.txt
src/Baluster.egg-info/not-zip-safe
src/Baluster.egg-info/top_level.txt
src/baluster/__init__.py
src/baluster/baluster.py
src/baluster/exceptions.py
src/baluster/makers.py
src/baluster/manager.py
src/baluster/mediator.py
src/baluster/placeholders.py
src/baluster/state.py
src/baluster/utils.py