Metadata-Version: 1.2
Name: Baluster
Version: 0.2.1
Summary: Provides hierarchical factory
Home-page: https://gitlab.com/palankai/baluster
Author: Csaba Palankai
Author-email: csaba.palankai@gmail.com
License: MIT
Keywords: context,context manager,async
Platform: UNKNOWN
Classifier: Development Status :: 3 - Alpha
Classifier: Intended Audience :: Developers
Classifier: License :: OSI Approved :: MIT License
Classifier: Natural Language :: English
Classifier: Programming Language :: Python :: 3.6
Classifier: Operating System :: OS Independent
Requires-Python: >=3.6
